Workbook

Sheet Insights 👀
B1: Budget & transaction tracking template
B3: 📍 Select File > Make a copy before editing this sheet; note that only red highighted cells are editable
B4: 📍 Log your transactions in the Transactions tab, then metrics below will auto-magically populate!
B5: 📍 Input your planned income and expenses in the red highlighted cells, then explore your own insights!
B6: Summary | H6: Expense Breakdown
B11: Income | C11: =IFERROR(__xludf.DUMMYFUNCTION("SPARKLINE($E$35,{""charttype"",""bar"";""max"",max($E$35,$K$35);""color1"",""#337A6B""})"),"")
B13: Expenses | C13: =IFERROR(__xludf.DUMMYFUNCTION("SPARKLINE($K$35,{""charttype"",""bar"";""max"",max($E$35,$K$35);""color1"",""#B78055""})"),"")
D17: =if(OR($E$35<=0,$K$35<=0),"❗️Oops! It looks like your income and/or expenses are less than or equal to $0. Ensure that your transactions are properly copied and loading below, then try again!",if($E$35>$K$35,"🔥 Woohoo! Your income was greater than your expenses this month. What are you going to do with the savings?","💩 Oh no! It looks like you spent more than you earned this month. It's OK though, take a close look at your expenses and see how you might be able to save next time 😉")) -> 🔥 Woohoo! Your income was greater than your expenses this month. What are you going to do with the savings?
B18: Savings
B20: =$E$35-$K$35 -> 938.22
B27: Income | H27: Expenses
B30: Planned | C30: =IFERROR(__xludf.DUMMYFUNCTION("SPARKLINE($D$35,{""charttype"",""bar"";""max"",max($D$35:$E$35);""color1"",""#B78055""})"),"") | F30: =if($E$35>=$D$35,"🙌","🙁") -> 🙌 | H30: Planned | I30: =IFERROR(__xludf.DUMMYFUNCTION("SPARKLINE($J$35,{""charttype"",""bar"";""max"",max($J$35:$K$35);""color1"",""#B78055""})"),"") | L30: =if($J$35>=$K$35,"🙌","🙁") -> 🙌
B31: Actual | C31: =IFERROR(__xludf.DUMMYFUNCTION("SPARKLINE($E$35,{""charttype"",""bar"";""max"",max($D$35:$E$35);""color1"",""#337A6B""})"),"") | H31: Actual | I31: =IFERROR(__xludf.DUMMYFUNCTION("SPARKLINE($K$35,{""charttype"",""bar"";""max"",max($J$35:$K$35);""color1"",""#337A6B""})"),"")
D34: Planned | E34: Actual | F34: Diff | J34: Planned | K34: Actual | L34: Diff
B35: Totals | D35: =sum(D37:D60) -> 3000 | E35: =sum(E37:E60) -> 3300 | F35: =E35-D35 -> 300 | H35: Totals | J35: =sum(J37:J60) -> 2940 | K35: =sum(K37:K60) -> 2361.78 | L35: =K35-J35 -> -578.22
B37: 🔨 Work | D37: 3000 | E37: =SUMIF('Transactions Start Here 🚀'!F:F,B37,'Transactions Start Here 🚀'!C:C) -> 3000 | F37: =E37-D37 -> 0 | H37: 🏡 Rent | J37: 1190 | K37: =SUMIF('Transactions Start Here 🚀'!L:L,H37,'Transactions Start Here 🚀'!I:I) -> 1190 | L37: =K37-J37 -> 0
B38: 💵 Other | D38: 0 | E38: =SUMIF('Transactions Start Here 🚀'!F:F,B38,'Transactions Start Here 🚀'!C:C) -> 300 | F38: =E38-D38 -> 300 | H38: 🥝 Grocery | J38: 400 | K38: =SUMIF('Transactions Start Here 🚀'!L:L,H38,'Transactions Start Here 🚀'!I:I) -> 293.52 | L38: =K38-J38 -> -106.48
B39: Custom-1 | D39: 0 | E39: =SUMIF('Transactions Start Here 🚀'!F:F,B39,'Transactions Start Here 🚀'!C:C) -> 0 | F39: =E39-D39 -> 0 | H39: 🍔 Dining | J39: 150 | K39: =SUMIF('Transactions Start Here 🚀'!L:L,H39,'Transactions Start Here 🚀'!I:I) -> 31.8 | L39: =K39-J39 -> -118.2
H40: 🚘 Transportation | J40: 70 | K40: =SUMIF('Transactions Start Here 🚀'!L:L,H40,'Transactions Start Here 🚀'!I:I) -> 83.22 | L40: =K40-J40 -> 13.22
H41: 🛍 Shopping | J41: 100 | K41: =SUMIF('Transactions Start Here 🚀'!L:L,H41,'Transactions Start Here 🚀'!I:I) -> 82.12 | L41: =K41-J41 -> -17.88
H42: 📚 Loan | J42: 0 | K42: =SUMIF('Transactions Start Here 🚀'!L:L,H42,'Transactions Start Here 🚀'!I:I) -> 0 | L42: =K42-J42 -> 0
H43: 🐶 Pet | J43: 150 | K43: =SUMIF('Transactions Start Here 🚀'!L:L,H43,'Transactions Start Here 🚀'!I:I) -> 50.94 | L43: =K43-J43 -> -99.06
H44: ⚡️ Utility | J44: 90 | K44: =SUMIF('Transactions Start Here 🚀'!L:L,H44,'Transactions Start Here 🚀'!I:I) -> 90 | L44: =K44-J44 -> 0
H45: 💫 Personal | J45: 50 | K45: =SUMIF('Transactions Start Here 🚀'!L:L,H45,'Transactions Start Here 🚀'!I:I) -> 37 | L45: =K45-J45 -> -13
H46: 🧷 Insurance | J46: 70 | K46: =SUMIF('Transactions Start Here 🚀'!L:L,H46,'Transactions Start Here 🚀'!I:I) -> 110.35 | L46: =K46-J46 -> 40.35
H47: 📞 Phone | J47: 40 | K47: =SUMIF('Transactions Start Here 🚀'!L:L,H47,'Transactions Start Here 🚀'!I:I) -> 44.95 | L47: =K47-J47 -> 4.95
H48: 💪 Gym | J48: 50
H49: 🧘‍♂️ Wellness | J49: 50 | K49: =SUMIF('Transactions Start Here 🚀'!L:L,H49,'Transactions Start Here 🚀'!I:I) -> 88.05 | L49: =K49-J49 -> 38.05
H50: ✈️ Travel | J50: 100 | K50: =SUMIF('Transactions Start Here 🚀'!L:L,H50,'Transactions Start Here 🚀'!I:I) -> 179.24 | L50: =K50-J50 -> 79.24
H51: 🏡 Home Good | J51: 150 | K51: =SUMIF('Transactions Start Here 🚀'!L:L,H51,'Transactions Start Here 🚀'!I:I) -> 0 | L51: =K51-J51 -> -150
H52: 👩‍⚕️ Medical | J52: 120 | K52: =SUMIF('Transactions Start Here 🚀'!L:L,H52,'Transactions Start Here 🚀'!I:I) -> 0 | L52: =K52-J52 -> -120
H53: 🎗 Giving | J53: 60 | K53: =SUMIF('Transactions Start Here 🚀'!L:L,H53,'Transactions Start Here 🚀'!I:I) -> 39.12 | L53: =K53-J53 -> -20.88
H54: 🍿 Entertainment | J54: 50 | K54: =SUMIF('Transactions Start Here 🚀'!L:L,H54,'Transactions Start Here 🚀'!I:I) -> 33.94 | L54: =K54-J54 -> -16.06
H55: 💵 Interest | J55: 0 | K55: =SUMIF('Transactions Start Here 🚀'!L:L,H55,'Transactions Start Here 🚀'!I:I) -> 0 | L55: =K55-J55 -> 0
H56: 🙉 Other | J56: 50 | K56: =SUMIF('Transactions Start Here 🚀'!L:L,H56,'Transactions Start Here 🚀'!I:I) -> 7.53 | L56: =K56-J56 -> -42.47
H57: Custom-1 | J57: 0 | K57: =SUMIF('Transactions Start Here 🚀'!L:L,H57,'Transactions Start Here 🚀'!I:I) -> 0 | L57: =K57-J57 -> 0
H58: Custom-2 | J58: 0 | K58: =SUMIF('Transactions Start Here 🚀'!L:L,H58,'Transactions Start Here 🚀'!I:I) -> 0 | L58: =K58-J58 -> 0
H59: Custom-3 | J59: 0 | K59: =SUMIF('Transactions Start Here 🚀'!L:L,H59,'Transactions Start Here 🚀'!I:I) -> 0 | L59: =K59-J59 -> 0

Sheet Transactions Start Here 🚀
B1: Budget & transaction tracking template
B3: 📍 Gather and log a full month's worth of card and bank transactions (required: amount and category)
B4: 📍 Ignore transfers (e.g. a payment from a bank account to a card; from a bank to an investment account, etc.)
B5: 📍 Add categories by editing the Custom-# cell(s) on the Insights tab; it will now show in the category dropdown
B6: Income | H6: Expenses
B10: Date | C10: Amount | D10: Title | F10: Category | H10: Date | I10: Amount | J10: Title | L10: Category
B11: 43952 | C11: 1500 | D11: Paycheck | F11: 🔨 Work | H11: 43952 | I11: 45.23 | J11: Whole Foods | L11: 🥝 Grocery
B12: 43966 | C12: 1500 | D12: Paycheck | F12: 🔨 Work | H12: 43953 | I12: 11.49 | J12: Moonflower | L12: 🥝 Grocery
B13: 43966 | C13: 300 | D13: Commission | F13: 💵 Other | H13: 43955 | I13: 75 | J13: Gym | L13: 🧘‍♂️ Wellness
H14: 43956 | I14: 53.12 | J14: Safeway | L14: 🥝 Grocery
H15: 43957 | I15: 179.24 | J15: Airbnb | L15: ✈️ Travel
H16: 43958 | I16: 39.2 | J16: Chevron | L16: 🚘 Transportation
H17: 43958 | I17: 110.35 | J17: State Farm | L17: 🧷 Insurance
H18: 43960 | I18: 39.12 | J18: Gift | L18: 🎗 Giving
H19: 43961 | I19: 37 | J19: Glossier | L19: 💫 Personal
H20: 43963 | I20: 22 | J20: Happy Hour | L20: 🍔 Dining
H21: 43964 | I21: 34.32 | J21: Trader Joe's | L21: 🥝 Grocery
H22: 43965 | I22: 4.9 | J22: Coffee Shop | L22: 🍔 Dining
H23: 43965 | I23: 50.94 | J23: Amazon (Dog Food) | L23: 🐶 Pet
H24: 43968 | I24: 44.24 | J24: Moonflower | L24: 🥝 Grocery
H25: 43970 | I25: 13.05 | J25: City Books | L25: 🧘‍♂️ Wellness
... H36: 43981 | I36: 4.9 | J36: Cofee Shop | L36: 🍔 Dining
