Workbook
Name coeff_made_copy: '🌀 Learn more about Coefficient'!$H$15
Name coeff_ok_check: '🌀 Learn more about Coefficient'!$B$15
Name coeff_importrange_check: '🌀 Learn more about Coefficient'!$C$15
Name coeff_addon_launched: '🌀 Learn more about Coefficient'!$E$15

Sheet Template
B3: QuickBooks 12-months Rolling Forecast
B4: Input your categories, items and actual values for the trailing twelve months in the Actuals and Forecasts tab. The 12-month rolling forecasts are computed based on a linear regression model.
I7: =IFERROR(__xludf.DUMMYFUNCTION("QUERY({B24:E137},""select Col1,sum(Col3),sum(Col4) where Col1 is not null group by Col1 label Col1 'Category',sum(Col3) 'TTM Actuals',sum(Col4) 'Rolling Forecast'"",0)"),"Category") -> Category | J7: =IFERROR(__xludf.DUMMYFUNCTION("""COMPUTED_VALUE"""),"TTM Actuals") -> TTM Actuals | K7: =IFERROR(__xludf.DUMMYFUNCTION("""COMPUTED_VALUE"""),"Rolling Forecast") -> Rolling Forecast | L7: TTM Labels | M7: RF Labels | O7: Expenses | P7: TTM Actuals | Q7: Rolling Forecast | R7: TTM Labels | S7: RF Labels
I8: =IFERROR(__xludf.DUMMYFUNCTION("""COMPUTED_VALUE"""),"Capital Expenditures") -> Capital Expenditures | J8: =IFERROR(__xludf.DUMMYFUNCTION("""COMPUTED_VALUE"""),157700.0) -> 157700 | K8: =IFERROR(__xludf.DUMMYFUNCTION("""COMPUTED_VALUE"""),175838.62152443972) -> 175838.62 | L8: =BYROW(J8:J137,LAMBDA(x,IF(x="",,TEXT(x,IF(x>=1000000,"$#.#,,",IF(x>=1000,"$#.#,","$#,###")))&IF(x>=1000000,"M",IF(x>=1000,"k",))))) -> $157.7k | M8: =BYROW(K8:K137,LAMBDA(x,IF(x="",,TEXT(x,IF(x>=1000000,"$#.#,,",IF(x>=1000,"$#.#,","$#,###")))&IF(x>=1000000,"M",IF(x>=1000,"k",))))) -> $175.8k | O8: =IFERROR(__xludf.DUMMYFUNCTION("IFERROR(SORT(FILTER(C24:E137,B24:B137=""Expenses""),2,0))"),"Salaries and Wages") -> Salaries and Wages | P8: =IFERROR(__xludf.DUMMYFUNCTION("""COMPUTED_VALUE"""),910000.0) -> 910000 | Q8: =IFERROR(__xludf.DUMMYFUNCTION("""COMPUTED_VALUE"""),919008.4578238048) -> 919008.46 | R8: =BYROW(P8:P137,LAMBDA(x,IF(x="",,TEXT(x,IF(x>=1000000,"$#.#,,",IF(x>=1000,"$#.#,","$#,###")))&IF(x>=1000000,"M",IF(x>=1000,"k",))))) -> $910.k | S8: =BYROW(Q8:Q137,LAMBDA(x,IF(x="",,TEXT(x,IF(x>=1000000,"$#.#,,",IF(x>=1000,"$#.#,","$#,###")))&IF(x>=1000000,"M",IF(x>=1000,"k",))))) -> $919.k
I9: =IFERROR(__xludf.DUMMYFUNCTION("""COMPUTED_VALUE"""),"Expenses") -> Expenses | J9: =IFERROR(__xludf.DUMMYFUNCTION("""COMPUTED_VALUE"""),1446100.0) -> 1446100 | K9: =IFERROR(__xludf.DUMMYFUNCTION("""COMPUTED_VALUE"""),1472212.3015278913) -> 1472212.3 | L9: $1.4M | M9: $1.5M | O9: =IFERROR(__xludf.DUMMYFUNCTION("""COMPUTED_VALUE"""),"Marketing and Sales") -> Marketing and Sales | P9: =IFERROR(__xludf.DUMMYFUNCTION("""COMPUTED_VALUE"""),244500.0) -> 244500 | Q9: =IFERROR(__xludf.DUMMYFUNCTION("""COMPUTED_VALUE"""),248409.5928926877) -> 248409.59 | R9: $244.5k | S9: $248.4k
I10: =IFERROR(__xludf.DUMMYFUNCTION("""COMPUTED_VALUE"""),"Revenue") -> Revenue | J10: =IFERROR(__xludf.DUMMYFUNCTION("""COMPUTED_VALUE"""),821700.0) -> 821700 | K10: =IFERROR(__xludf.DUMMYFUNCTION("""COMPUTED_VALUE"""),838397.0459787921) -> 838397.05 | L10: $821.7k | M10: $838.4k | O10: =IFERROR(__xludf.DUMMYFUNCTION("""COMPUTED_VALUE"""),"Cloud Hosting") -> Cloud Hosting | P10: =IFERROR(__xludf.DUMMYFUNCTION("""COMPUTED_VALUE"""),189700.0) -> 189700 | Q10: =IFERROR(__xludf.DUMMYFUNCTION("""COMPUTED_VALUE"""),199190.27971974807) -> 199190.28 | R10: $189.7k | S10: $199.2k
O11: =IFERROR(__xludf.DUMMYFUNCTION("""COMPUTED_VALUE"""),"Software Licenses") -> Software Licenses | P11: =IFERROR(__xludf.DUMMYFUNCTION("""COMPUTED_VALUE"""),61900.0) -> 61900 | Q11: =IFERROR(__xludf.DUMMYFUNCTION("""COMPUTED_VALUE"""),64177.95611473016) -> 64177.956 | R11: $61.9k | S11: $64.2k
O12: =IFERROR(__xludf.DUMMYFUNCTION("""COMPUTED_VALUE"""),"Customer Support") -> Customer Support | P12: =IFERROR(__xludf.DUMMYFUNCTION("""COMPUTED_VALUE"""),40000.0) -> 40000 | Q12: =IFERROR(__xludf.DUMMYFUNCTION("""COMPUTED_VALUE"""),41426.01497692065) -> 41426.015 | R12: $40.k | S12: $41.4k
B22: Category | C22: Item | D22: TTM Actuals | E22: Rolling Forecast | F22: $ Increase (Decrease) | G22: % Increase (Decrease)
D23: =IFERROR("("&TEXT('Actuals and Forecasts'!D4,"mmm-yyyy")&" to "&TEXT('Actuals and Forecasts'!O4,"mmm-yyyy")&")","") -> (Sep-2025 to Aug-2026) | E23: =IFERROR("("&TEXT('Actuals and Forecasts'!P4,"mmm-yyyy")&" to "&TEXT('Actuals and Forecasts'!AA4,"mmm-yyyy")&")","") -> (Sep-2026 to Aug-2027)
B24: {=UNIQUE('Actuals and Forecasts'!B5:C137)} -> Revenue | C24: Subscription Revenue | D24: {=MAP(B24:B137,C24:C137,LAMBDA(x,y,IF(y="",,SUMIFS('Actuals and Forecasts'!AB:AB,'Actuals and Forecasts'!B:B,x,'Actuals and Forecasts'!C:C,y))))} -> 587500 | E24: {=MAP(B24:B137,C24:C137,LAMBDA(x,y,IF(y="",,SUMIFS('Actuals and Forecasts'!AC:AC,'Actuals and Forecasts'!B:B,x,'Actuals and Forecasts'!C:C,y))))} -> 599000.93 | F24: {=MAP(D24:D137,E24:E137,LAMBDA(x,y,IF(x="",,y-x)))} -> 11500.927 | G24: {=MAP(D24:D137,F24:F137,LAMBDA(x,y,IF(x="",,y/x)))} -> 0.019576047
B25: Revenue | C25: Setup Fees | D25: 108500 | E25: 108772.87 | F25: 272.86569 | G25: 0.0025148911
B26: Revenue | C26: Professional Services | D26: 61400 | E26: 63031.637 | F26: 1631.6368 | G26: 0.026573889
B27: Revenue | C27: Partner Integrations | D27: 38800 | E27: 41129.639 | F27: 2329.6394 | G27: 0.060042253
B28: Revenue | C28: Advertising Revenue | D28: 25500 | E28: 26461.977 | F28: 961.97659 | G28: 0.037724572
B29: Expenses | C29: Cloud Hosting | D29: 189700 | E29: 199190.28 | F29: 9490.2797 | G29: 0.050027832
B30: Expenses | C30: Salaries and Wages | D30: 910000 | E30: 919008.46 | F30: 9008.4578 | G30: 0.0098994042
B31: Expenses | C31: Marketing and Sales | D31: 244500 | E31: 248409.59 | F31: 3909.5929 | G31: 0.015990155
B32: Expenses | C32: Software Licenses | D32: 61900 | E32: 64177.956 | F32: 2277.9561 | G32: 0.036800583
B33: Expenses | C33: Customer Support | D33: 40000 | E33: 41426.015 | F33: 1426.015 | G33: 0.035650374
B34: Capital Expenditures | C34: Platform Development | D34: 57100 | E34: 66046.771 | F34: 8946.7713 | G34: 0.15668601
B35: Capital Expenditures | C35: IT Hardware | D35: 23500 | E35: 26478.182 | F35: 2978.1817 | G35: 0.12673114
B36: Capital Expenditures | C36: Office Buildout | D36: 32200 | E36: 33419.282 | F36: 1219.2817 | G36: 0.037865892
... B38: Capital Expenditures | C38: Business Intelligence | D38: 28100 | E38: 31080.405 | F38: 2980.4046 | G38: 0.10606422

Sheet Actuals and Forecasts
B2: Trailing Twelve Months (TTM) Actuals | P2: 12-month Rolling Forecast
B3: Include here your categories, items and actual amounts for the past 12 months | P3: This table computes the rolling forecast for the next 12 months
B4: Categories | C4: Item | D4: =EOMONTH(E4,-2)+1 -> 45901 | E4: =EOMONTH(F4,-2)+1 -> 45931 | F4: =EOMONTH(G4,-2)+1 -> 45962 | G4: =EOMONTH(H4,-2)+1 -> 45992 | H4: =EOMONTH(I4,-2)+1 -> 46023 | I4: =EOMONTH(J4,-2)+1 -> 46054 | J4: =EOMONTH(K4,-2)+1 -> 46082 | K4: =EOMONTH(L4,-2)+1 -> 46113 | ... N4: =EOMONTH(O4,-2)+1 -> 46204 | O4: =EOMONTH(TODAY(),-1)+1 -> 46235 | P4: =EOMONTH(O4,)+1 -> 46266 | Q4: =EOMONTH(P4,)+1 -> 46296 | R4: =EOMONTH(Q4,)+1 -> 46327 | S4: =EOMONTH(R4,)+1 -> 46357 | T4: =EOMONTH(S4,)+1 -> 46388 | U4: =EOMONTH(T4,)+1 -> 46419 | V4: =EOMONTH(U4,)+1 -> 46447 | W4: =EOMONTH(V4,)+1 -> 46478 | ... AA4: =EOMONTH(Z4,)+1 -> 46600 | AB4: {={"Total Actuals";BYROW(D5:O30,LAMBDA(x,IFERROR(LET(a,SUM(x),IF(a<>0,a,)),"")))}} -> Total Actuals | AC4: {={"Total Forecasts";BYROW(P5:AA30,LAMBDA(x,IFERROR(LET(a,SUM(x),IF(a<>0,a,)),"")))}} -> Total Forecasts
B5: Revenue | C5: Subscription Revenue | D5: 48000 | E5: 47500 | F5: 49000 | G5: 50200 | H5: 48700 | I5: 49300 | J5: 48500 | K5: 50100 | L5: 48800 | M5: 49400 | N5: 49500 | O5: 48500 | P5: =IFERROR(FORECAST(P$4,$D5:$O5,$D$4:$O$4),"") -> 49478.676 | Q5: =IFERROR(FORECAST(Q$4,$D5:$O5,$D$4:$O$4),"") -> 49557.449 | R5: =IFERROR(FORECAST(R$4,$D5:$O5,$D$4:$O$4),"") -> 49638.849 | S5: =IFERROR(FORECAST(S$4,$D5:$O5,$D$4:$O$4),"") -> 49717.622 | T5: =IFERROR(FORECAST(T$4,$D5:$O5,$D$4:$O$4),"") -> 49799.021 | U5: =IFERROR(FORECAST(U$4,$D5:$O5,$D$4:$O$4),"") -> 49880.421 | V5: =IFERROR(FORECAST(V$4,$D5:$O5,$D$4:$O$4),"") -> 49953.943 | W5: =IFERROR(FORECAST(W$4,$D5:$O5,$D$4:$O$4),"") -> 50035.342 | ... AA5: =IFERROR(FORECAST(AA$4,$D5:$O5,$D$4:$O$4),"") -> 50355.687 | AB5: 587500 | AC5: 599000.93
B6: Revenue | C6: Setup Fees | D6: 9000 | E6: 9300 | F6: 8500 | G6: 9000 | H6: 9200 | I6: 9500 | J6: 8700 | K6: 9100 | L6: 9400 | M6: 8800 | N6: 8900 | O6: 9100 | P6: =IFERROR(FORECAST(P$4,$D6:$O6,$D$4:$O$4),"") -> 9054.0121 | Q6: =IFERROR(FORECAST(Q$4,$D6:$O6,$D$4:$O$4),"") -> 9055.881 | R6: =IFERROR(FORECAST(R$4,$D6:$O6,$D$4:$O$4),"") -> 9057.8123 | S6: =IFERROR(FORECAST(S$4,$D6:$O6,$D$4:$O$4),"") -> 9059.6812 | T6: =IFERROR(FORECAST(T$4,$D6:$O6,$D$4:$O$4),"") -> 9061.6124 | U6: =IFERROR(FORECAST(U$4,$D6:$O6,$D$4:$O$4),"") -> 9063.5437 | V6: =IFERROR(FORECAST(V$4,$D6:$O6,$D$4:$O$4),"") -> 9065.288 | W6: =IFERROR(FORECAST(W$4,$D6:$O6,$D$4:$O$4),"") -> 9067.2193 | ... AA6: =IFERROR(FORECAST(AA$4,$D6:$O6,$D$4:$O$4),"") -> 9074.8196 | AB6: 108500 | AC6: 108772.87
B7: Revenue | C7: Professional Services | D7: 5000 | E7: 5200 | F7: 4800 | G7: 5500 | H7: 4900 | I7: 5300 | J7: 4700 | K7: 5400 | L7: 5100 | M7: 5200 | N7: 5000 | O7: 5300 | P7: =IFERROR(FORECAST(P$4,$D7:$O7,$D$4:$O$4),"") -> 5190.4877 | Q7: =IFERROR(FORECAST(Q$4,$D7:$O7,$D$4:$O$4),"") -> 5201.6633 | R7: =IFERROR(FORECAST(R$4,$D7:$O7,$D$4:$O$4),"") -> 5213.2114 | S7: =IFERROR(FORECAST(S$4,$D7:$O7,$D$4:$O$4),"") -> 5224.387 | T7: =IFERROR(FORECAST(T$4,$D7:$O7,$D$4:$O$4),"") -> 5235.9351 | U7: =IFERROR(FORECAST(U$4,$D7:$O7,$D$4:$O$4),"") -> 5247.4832 | V7: =IFERROR(FORECAST(V$4,$D7:$O7,$D$4:$O$4),"") -> 5257.9138 | W7: =IFERROR(FORECAST(W$4,$D7:$O7,$D$4:$O$4),"") -> 5269.4619 | ... AA7: =IFERROR(FORECAST(AA$4,$D7:$O7,$D$4:$O$4),"") -> 5314.9093 | AB7: 61400 | AC7: 63031.637
B8: Revenue | C8: Partner Integrations | D8: 3200 | E8: 3000 | F8: 3100 | G8: 3400 | H8: 3200 | I8: 3300 | J8: 3100 | K8: 3300 | L8: 3400 | M8: 3200 | N8: 3300 | O8: 3300 | P8: =IFERROR(FORECAST(P$4,$D8:$O8,$D$4:$O$4),"") -> 3338.7344 | Q8: =IFERROR(FORECAST(Q$4,$D8:$O8,$D$4:$O$4),"") -> 3354.6909 | R8: =IFERROR(FORECAST(R$4,$D8:$O8,$D$4:$O$4),"") -> 3371.1792 | S8: =IFERROR(FORECAST(S$4,$D8:$O8,$D$4:$O$4),"") -> 3387.1356 | T8: =IFERROR(FORECAST(T$4,$D8:$O8,$D$4:$O$4),"") -> 3403.6239 | U8: =IFERROR(FORECAST(U$4,$D8:$O8,$D$4:$O$4),"") -> 3420.1123 | V8: =IFERROR(FORECAST(V$4,$D8:$O8,$D$4:$O$4),"") -> 3435.0049 | W8: =IFERROR(FORECAST(W$4,$D8:$O8,$D$4:$O$4),"") -> 3451.4933 | ... AA8: =IFERROR(FORECAST(AA$4,$D8:$O8,$D$4:$O$4),"") -> 3516.3828 | AB8: 38800 | AC8: 41129.639
B9: Revenue | C9: Advertising Revenue | D9: 2000 | E9: 2200 | F9: 1800 | G9: 2400 | H9: 2100 | I9: 2200 | J9: 2000 | K9: 2300 | L9: 2100 | M9: 2200 | N9: 2100 | O9: 2100 | P9: =IFERROR(FORECAST(P$4,$D9:$O9,$D$4:$O$4),"") -> 2168.5232 | Q9: =IFERROR(FORECAST(Q$4,$D9:$O9,$D$4:$O$4),"") -> 2175.1121 | R9: =IFERROR(FORECAST(R$4,$D9:$O9,$D$4:$O$4),"") -> 2181.9206 | S9: =IFERROR(FORECAST(S$4,$D9:$O9,$D$4:$O$4),"") -> 2188.5095 | T9: =IFERROR(FORECAST(T$4,$D9:$O9,$D$4:$O$4),"") -> 2195.318 | U9: =IFERROR(FORECAST(U$4,$D9:$O9,$D$4:$O$4),"") -> 2202.1265 | V9: =IFERROR(FORECAST(V$4,$D9:$O9,$D$4:$O$4),"") -> 2208.2761 | W9: =IFERROR(FORECAST(W$4,$D9:$O9,$D$4:$O$4),"") -> 2215.0846 | ... AA9: =IFERROR(FORECAST(AA$4,$D9:$O9,$D$4:$O$4),"") -> 2241.8794 | AB9: 25500 | AC9: 26461.977
B10: Expenses | C10: Cloud Hosting | D10: 15500 | E10: 15000 | F10: 15500 | G10: 16200 | H10: 15800 | I10: 16200 | J10: 15400 | K10: 16000 | L10: 15700 | M10: 16100 | N10: 16300 | O10: 16000 | P10: =IFERROR(FORECAST(P$4,$D10:$O10,$D$4:$O$4),"") -> 16237.707 | Q10: =IFERROR(FORECAST(Q$4,$D10:$O10,$D$4:$O$4),"") -> 16302.709 | R10: =IFERROR(FORECAST(R$4,$D10:$O10,$D$4:$O$4),"") -> 16369.878 | S10: =IFERROR(FORECAST(S$4,$D10:$O10,$D$4:$O$4),"") -> 16434.88 | T10: =IFERROR(FORECAST(T$4,$D10:$O10,$D$4:$O$4),"") -> 16502.048 | U10: =IFERROR(FORECAST(U$4,$D10:$O10,$D$4:$O$4),"") -> 16569.217 | V10: =IFERROR(FORECAST(V$4,$D10:$O10,$D$4:$O$4),"") -> 16629.885 | W10: =IFERROR(FORECAST(W$4,$D10:$O10,$D$4:$O$4),"") -> 16697.054 | ... AA10: =IFERROR(FORECAST(AA$4,$D10:$O10,$D$4:$O$4),"") -> 16961.395 | AB10: 189700 | AC10: 199190.28
B11: Expenses | C11: Salaries and Wages | D11: 75000 | E11: 75500 | F11: 76000 | G11: 75500 | H11: 75700 | I11: 76200 | J11: 75800 | K11: 76400 | L11: 75900 | M11: 76300 | N11: 76100 | O11: 75600 | P11: =IFERROR(FORECAST(P$4,$D11:$O11,$D$4:$O$4),"") -> 76240.908 | Q11: =IFERROR(FORECAST(Q$4,$D11:$O11,$D$4:$O$4),"") -> 76302.61 | R11: =IFERROR(FORECAST(R$4,$D11:$O11,$D$4:$O$4),"") -> 76366.368 | S11: =IFERROR(FORECAST(S$4,$D11:$O11,$D$4:$O$4),"") -> 76428.07 | T11: =IFERROR(FORECAST(T$4,$D11:$O11,$D$4:$O$4),"") -> 76491.828 | U11: =IFERROR(FORECAST(U$4,$D11:$O11,$D$4:$O$4),"") -> 76555.587 | V11: =IFERROR(FORECAST(V$4,$D11:$O11,$D$4:$O$4),"") -> 76613.175 | W11: =IFERROR(FORECAST(W$4,$D11:$O11,$D$4:$O$4),"") -> 76676.934 | ... AA11: =IFERROR(FORECAST(AA$4,$D11:$O11,$D$4:$O$4),"") -> 76927.854 | AB11: 910000 | AC11: 919008.46
B12: Expenses | C12: Marketing and Sales | D12: 20000 | E12: 20300 | F12: 20100 | G12: 20500 | H12: 20400 | I12: 20700 | J12: 20200 | K12: 20600 | L12: 20500 | M12: 20400 | N12: 20300 | O12: 20500 | P12: =IFERROR(FORECAST(P$4,$D12:$O12,$D$4:$O$4),"") -> 20551.884 | Q12: =IFERROR(FORECAST(Q$4,$D12:$O12,$D$4:$O$4),"") -> 20578.662 | R12: =IFERROR(FORECAST(R$4,$D12:$O12,$D$4:$O$4),"") -> 20606.332 | S12: =IFERROR(FORECAST(S$4,$D12:$O12,$D$4:$O$4),"") -> 20633.11 | T12: =IFERROR(FORECAST(T$4,$D12:$O12,$D$4:$O$4),"") -> 20660.781 | U12: =IFERROR(FORECAST(U$4,$D12:$O12,$D$4:$O$4),"") -> 20688.452 | V12: =IFERROR(FORECAST(V$4,$D12:$O12,$D$4:$O$4),"") -> 20713.445 | W12: =IFERROR(FORECAST(W$4,$D12:$O12,$D$4:$O$4),"") -> 20741.115 | ... AA12: =IFERROR(FORECAST(AA$4,$D12:$O12,$D$4:$O$4),"") -> 20850.013 | AB12: 244500 | AC12: 248409.59
B13: Expenses | C13: Software Licenses | D13: 5000 | E13: 5100 | F13: 5200 | G13: 5000 | H13: 5300 | I13: 5100 | J13: 5200 | K13: 5100 | L13: 5200 | M13: 5300 | N13: 5100 | O13: 5300 | P13: =IFERROR(FORECAST(P$4,$D13:$O13,$D$4:$O$4),"") -> 5261.3961 | Q13: =IFERROR(FORECAST(Q$4,$D13:$O13,$D$4:$O$4),"") -> 5276.9986 | R13: =IFERROR(FORECAST(R$4,$D13:$O13,$D$4:$O$4),"") -> 5293.1211 | S13: =IFERROR(FORECAST(S$4,$D13:$O13,$D$4:$O$4),"") -> 5308.7235 | T13: =IFERROR(FORECAST(T$4,$D13:$O13,$D$4:$O$4),"") -> 5324.846 | U13: =IFERROR(FORECAST(U$4,$D13:$O13,$D$4:$O$4),"") -> 5340.9686 | V13: =IFERROR(FORECAST(V$4,$D13:$O13,$D$4:$O$4),"") -> 5355.5308 | W13: =IFERROR(FORECAST(W$4,$D13:$O13,$D$4:$O$4),"") -> 5371.6533 | ... AA13: =IFERROR(FORECAST(AA$4,$D13:$O13,$D$4:$O$4),"") -> 5435.1033 | AB13: 61900 | AC13: 64177.956
B14: Expenses | C14: Customer Support | D14: 3200 | E14: 3300 | F14: 3400 | G14: 3200 | H14: 3300 | I14: 3500 | J14: 3400 | K14: 3300 | L14: 3200 | M14: 3500 | N14: 3300 | O14: 3400 | P14: =IFERROR(FORECAST(P$4,$D14:$O14,$D$4:$O$4),"") -> 3397.8513 | Q14: =IFERROR(FORECAST(Q$4,$D14:$O14,$D$4:$O$4),"") -> 3407.6185 | R14: =IFERROR(FORECAST(R$4,$D14:$O14,$D$4:$O$4),"") -> 3417.7113 | S14: =IFERROR(FORECAST(S$4,$D14:$O14,$D$4:$O$4),"") -> 3427.4785 | T14: =IFERROR(FORECAST(T$4,$D14:$O14,$D$4:$O$4),"") -> 3437.5713 | U14: =IFERROR(FORECAST(U$4,$D14:$O14,$D$4:$O$4),"") -> 3447.6641 | V14: =IFERROR(FORECAST(V$4,$D14:$O14,$D$4:$O$4),"") -> 3456.7802 | W14: =IFERROR(FORECAST(W$4,$D14:$O14,$D$4:$O$4),"") -> 3466.873 | ... AA14: =IFERROR(FORECAST(AA$4,$D14:$O14,$D$4:$O$4),"") -> 3506.5931 | AB14: 40000 | AC14: 41426.015
B15: Capital Expenditures | C15: Platform Development | D15: 4500 | E15: 4800 | F15: 4200 | G15: 4700 | H15: 4600 | I15: 4800 | J15: 4700 | K15: 4500 | L15: 4900 | M15: 5000 | N15: 5100 | O15: 5300 | P15: =IFERROR(FORECAST(P$4,$D15:$O15,$D$4:$O$4),"") -> 5163.1169 | Q15: =IFERROR(FORECAST(Q$4,$D15:$O15,$D$4:$O$4),"") -> 5224.3961 | R15: =IFERROR(FORECAST(R$4,$D15:$O15,$D$4:$O$4),"") -> 5287.718 | S15: =IFERROR(FORECAST(S$4,$D15:$O15,$D$4:$O$4),"") -> 5348.9973 | T15: =IFERROR(FORECAST(T$4,$D15:$O15,$D$4:$O$4),"") -> 5412.3192 | U15: =IFERROR(FORECAST(U$4,$D15:$O15,$D$4:$O$4),"") -> 5475.6411 | V15: =IFERROR(FORECAST(V$4,$D15:$O15,$D$4:$O$4),"") -> 5532.835 | W15: =IFERROR(FORECAST(W$4,$D15:$O15,$D$4:$O$4),"") -> 5596.1569 | ... AA15: =IFERROR(FORECAST(AA$4,$D15:$O15,$D$4:$O$4),"") -> 5845.3592 | AB15: 57100 | AC15: 66046.771
B16: Capital Expenditures | C16: IT Hardware | D16: 1800 | E16: 1700 | F16: 2100 | G16: 1800 | H16: 2000 | I16: 1900 | J16: 2200 | K16: 1900 | L16: 2100 | M16: 2000 | N16: 1900 | O16: 2100 | P16: =IFERROR(FORECAST(P$4,$D16:$O16,$D$4:$O$4),"") -> 2093.0768 | Q16: =IFERROR(FORECAST(Q$4,$D16:$O16,$D$4:$O$4),"") -> 2113.4753 | R16: =IFERROR(FORECAST(R$4,$D16:$O16,$D$4:$O$4),"") -> 2134.5538 | S16: =IFERROR(FORECAST(S$4,$D16:$O16,$D$4:$O$4),"") -> 2154.9523 | T16: =IFERROR(FORECAST(T$4,$D16:$O16,$D$4:$O$4),"") -> 2176.0307 | U16: =IFERROR(FORECAST(U$4,$D16:$O16,$D$4:$O$4),"") -> 2197.1092 | V16: =IFERROR(FORECAST(V$4,$D16:$O16,$D$4:$O$4),"") -> 2216.1478 | W16: =IFERROR(FORECAST(W$4,$D16:$O16,$D$4:$O$4),"") -> 2237.2262 | ... AA16: =IFERROR(FORECAST(AA$4,$D16:$O16,$D$4:$O$4),"") -> 2320.1801 | AB16: 23500 | AC16: 26478.182
... B19: Capital Expenditures | C19: Business Intelligence | D19: 2200 | E19: 2100 | F19: 2300 | G19: 2400 | H19: 2500 | I19: 2200 | J19: 2400 | K19: 2300 | L19: 2500 | M19: 2400 | N19: 2300 | O19: 2500 | P19: =IFERROR(FORECAST(P$4,$D19:$O19,$D$4:$O$4),"") -> 2476.5107 | Q19: =IFERROR(FORECAST(Q$4,$D19:$O19,$D$4:$O$4),"") -> 2496.9244 | R19: =IFERROR(FORECAST(R$4,$D19:$O19,$D$4:$O$4),"") -> 2518.0186 | S19: =IFERROR(FORECAST(S$4,$D19:$O19,$D$4:$O$4),"") -> 2538.4323 | T19: =IFERROR(FORECAST(T$4,$D19:$O19,$D$4:$O$4),"") -> 2559.5265 | U19: =IFERROR(FORECAST(U$4,$D19:$O19,$D$4:$O$4),"") -> 2580.6207 | V19: =IFERROR(FORECAST(V$4,$D19:$O19,$D$4:$O$4),"") -> 2599.6735 | W19: =IFERROR(FORECAST(W$4,$D19:$O19,$D$4:$O$4),"") -> 2620.7677 | ... AA19: =IFERROR(FORECAST(AA$4,$D19:$O19,$D$4:$O$4),"") -> 2703.7836 | AB19: 28100 | AC19: 31080.405
P20: =IFERROR(FORECAST(P$4,$D20:$O20,$D$4:$O$4),"") | Q20: =IFERROR(FORECAST(Q$4,$D20:$O20,$D$4:$O$4),"") | R20: =IFERROR(FORECAST(R$4,$D20:$O20,$D$4:$O$4),"") | S20: =IFERROR(FORECAST(S$4,$D20:$O20,$D$4:$O$4),"") | T20: =IFERROR(FORECAST(T$4,$D20:$O20,$D$4:$O$4),"") | U20: =IFERROR(FORECAST(U$4,$D20:$O20,$D$4:$O$4),"") | V20: =IFERROR(FORECAST(V$4,$D20:$O20,$D$4:$O$4),"") | W20: =IFERROR(FORECAST(W$4,$D20:$O20,$D$4:$O$4),"") | ... AA20: =IFERROR(FORECAST(AA$4,$D20:$O20,$D$4:$O$4),"")
P21: =IFERROR(FORECAST(P$4,$D21:$O21,$D$4:$O$4),"") | Q21: =IFERROR(FORECAST(Q$4,$D21:$O21,$D$4:$O$4),"") | R21: =IFERROR(FORECAST(R$4,$D21:$O21,$D$4:$O$4),"") | S21: =IFERROR(FORECAST(S$4,$D21:$O21,$D$4:$O$4),"") | T21: =IFERROR(FORECAST(T$4,$D21:$O21,$D$4:$O$4),"") | U21: =IFERROR(FORECAST(U$4,$D21:$O21,$D$4:$O$4),"") | V21: =IFERROR(FORECAST(V$4,$D21:$O21,$D$4:$O$4),"") | W21: =IFERROR(FORECAST(W$4,$D21:$O21,$D$4:$O$4),"") | ... AA21: =IFERROR(FORECAST(AA$4,$D21:$O21,$D$4:$O$4),"")
P22: =IFERROR(FORECAST(P$4,$D22:$O22,$D$4:$O$4),"") | Q22: =IFERROR(FORECAST(Q$4,$D22:$O22,$D$4:$O$4),"") | R22: =IFERROR(FORECAST(R$4,$D22:$O22,$D$4:$O$4),"") | S22: =IFERROR(FORECAST(S$4,$D22:$O22,$D$4:$O$4),"") | T22: =IFERROR(FORECAST(T$4,$D22:$O22,$D$4:$O$4),"") | U22: =IFERROR(FORECAST(U$4,$D22:$O22,$D$4:$O$4),"") | V22: =IFERROR(FORECAST(V$4,$D22:$O22,$D$4:$O$4),"") | W22: =IFERROR(FORECAST(W$4,$D22:$O22,$D$4:$O$4),"") | ... AA22: =IFERROR(FORECAST(AA$4,$D22:$O22,$D$4:$O$4),"")
P23: =IFERROR(FORECAST(P$4,$D23:$O23,$D$4:$O$4),"") | Q23: =IFERROR(FORECAST(Q$4,$D23:$O23,$D$4:$O$4),"") | R23: =IFERROR(FORECAST(R$4,$D23:$O23,$D$4:$O$4),"") | S23: =IFERROR(FORECAST(S$4,$D23:$O23,$D$4:$O$4),"") | T23: =IFERROR(FORECAST(T$4,$D23:$O23,$D$4:$O$4),"") | U23: =IFERROR(FORECAST(U$4,$D23:$O23,$D$4:$O$4),"") | V23: =IFERROR(FORECAST(V$4,$D23:$O23,$D$4:$O$4),"") | W23: =IFERROR(FORECAST(W$4,$D23:$O23,$D$4:$O$4),"") | ... AA23: =IFERROR(FORECAST(AA$4,$D23:$O23,$D$4:$O$4),"")
P24: =IFERROR(FORECAST(P$4,$D24:$O24,$D$4:$O$4),"") | Q24: =IFERROR(FORECAST(Q$4,$D24:$O24,$D$4:$O$4),"") | R24: =IFERROR(FORECAST(R$4,$D24:$O24,$D$4:$O$4),"") | S24: =IFERROR(FORECAST(S$4,$D24:$O24,$D$4:$O$4),"") | T24: =IFERROR(FORECAST(T$4,$D24:$O24,$D$4:$O$4),"") | U24: =IFERROR(FORECAST(U$4,$D24:$O24,$D$4:$O$4),"") | V24: =IFERROR(FORECAST(V$4,$D24:$O24,$D$4:$O$4),"") | W24: =IFERROR(FORECAST(W$4,$D24:$O24,$D$4:$O$4),"") | ... AA24: =IFERROR(FORECAST(AA$4,$D24:$O24,$D$4:$O$4),"")
P25: =IFERROR(FORECAST(P$4,$D25:$O25,$D$4:$O$4),"") | Q25: =IFERROR(FORECAST(Q$4,$D25:$O25,$D$4:$O$4),"") | R25: =IFERROR(FORECAST(R$4,$D25:$O25,$D$4:$O$4),"") | S25: =IFERROR(FORECAST(S$4,$D25:$O25,$D$4:$O$4),"") | T25: =IFERROR(FORECAST(T$4,$D25:$O25,$D$4:$O$4),"") | U25: =IFERROR(FORECAST(U$4,$D25:$O25,$D$4:$O$4),"") | V25: =IFERROR(FORECAST(V$4,$D25:$O25,$D$4:$O$4),"") | W25: =IFERROR(FORECAST(W$4,$D25:$O25,$D$4:$O$4),"") | ... AA25: =IFERROR(FORECAST(AA$4,$D25:$O25,$D$4:$O$4),"")
P26: =IFERROR(FORECAST(P$4,$D26:$O26,$D$4:$O$4),"") | Q26: =IFERROR(FORECAST(Q$4,$D26:$O26,$D$4:$O$4),"") | R26: =IFERROR(FORECAST(R$4,$D26:$O26,$D$4:$O$4),"") | S26: =IFERROR(FORECAST(S$4,$D26:$O26,$D$4:$O$4),"") | T26: =IFERROR(FORECAST(T$4,$D26:$O26,$D$4:$O$4),"") | U26: =IFERROR(FORECAST(U$4,$D26:$O26,$D$4:$O$4),"") | V26: =IFERROR(FORECAST(V$4,$D26:$O26,$D$4:$O$4),"") | W26: =IFERROR(FORECAST(W$4,$D26:$O26,$D$4:$O$4),"") | ... AA26: =IFERROR(FORECAST(AA$4,$D26:$O26,$D$4:$O$4),"")
P27: =IFERROR(FORECAST(P$4,$D27:$O27,$D$4:$O$4),"") | Q27: =IFERROR(FORECAST(Q$4,$D27:$O27,$D$4:$O$4),"") | R27: =IFERROR(FORECAST(R$4,$D27:$O27,$D$4:$O$4),"") | S27: =IFERROR(FORECAST(S$4,$D27:$O27,$D$4:$O$4),"") | T27: =IFERROR(FORECAST(T$4,$D27:$O27,$D$4:$O$4),"") | U27: =IFERROR(FORECAST(U$4,$D27:$O27,$D$4:$O$4),"") | V27: =IFERROR(FORECAST(V$4,$D27:$O27,$D$4:$O$4),"") | W27: =IFERROR(FORECAST(W$4,$D27:$O27,$D$4:$O$4),"") | ... AA27: =IFERROR(FORECAST(AA$4,$D27:$O27,$D$4:$O$4),"")
P28: =IFERROR(FORECAST(P$4,$D28:$O28,$D$4:$O$4),"") | Q28: =IFERROR(FORECAST(Q$4,$D28:$O28,$D$4:$O$4),"") | R28: =IFERROR(FORECAST(R$4,$D28:$O28,$D$4:$O$4),"") | S28: =IFERROR(FORECAST(S$4,$D28:$O28,$D$4:$O$4),"") | T28: =IFERROR(FORECAST(T$4,$D28:$O28,$D$4:$O$4),"") | U28: =IFERROR(FORECAST(U$4,$D28:$O28,$D$4:$O$4),"") | V28: =IFERROR(FORECAST(V$4,$D28:$O28,$D$4:$O$4),"") | W28: =IFERROR(FORECAST(W$4,$D28:$O28,$D$4:$O$4),"") | ... AA28: =IFERROR(FORECAST(AA$4,$D28:$O28,$D$4:$O$4),"")
P29: =IFERROR(FORECAST(P$4,$D29:$O29,$D$4:$O$4),"") | Q29: =IFERROR(FORECAST(Q$4,$D29:$O29,$D$4:$O$4),"") | R29: =IFERROR(FORECAST(R$4,$D29:$O29,$D$4:$O$4),"") | S29: =IFERROR(FORECAST(S$4,$D29:$O29,$D$4:$O$4),"") | T29: =IFERROR(FORECAST(T$4,$D29:$O29,$D$4:$O$4),"") | U29: =IFERROR(FORECAST(U$4,$D29:$O29,$D$4:$O$4),"") | V29: =IFERROR(FORECAST(V$4,$D29:$O29,$D$4:$O$4),"") | W29: =IFERROR(FORECAST(W$4,$D29:$O29,$D$4:$O$4),"") | ... AA29: =IFERROR(FORECAST(AA$4,$D29:$O29,$D$4:$O$4),"")

Sheet 🌀 Learn more about Coefficient
B7: ➊ | C7: Install the Coefficient extension | F7: ➋ | G7: Launch Coefficient | J7: ➌ | K7: Connect your data!
D8: 👈 | G8: Click "Extensions" > "Coefficient" > "Launch" | K8: Click "Import from..." then select the source you'd like to import data from. With a simple selector and prompts along the way, you'll pull your first data import in just 60 seconds.
C9: In the popup window, click the "INSTALL" button Click “Continue” to accept permissions
C11: 🎥 See how it works
C13: ⚠️ If you run into an error, click here
B15: =_coeffs_ok() -> OK | C15: =IFERROR(__xludf.DUMMYFUNCTION("IMPORTRANGE(""https://docs.google.com/spreadsheets/d/1qFNrgBSxxEQBx4sdMB8uzwFvvIRsUBuGfUwyQgqeRN4/edit#gid=1503868715"",""A1"")"),"Date") -> Date | E15: TRUE | G15: Quickbooks Rolling Forecast Template | H15: =IFERROR(__xludf.DUMMYFUNCTION("and(iferror(ERROR.TYPE(_COEFFs_ok())=5,false),iferror(ERROR.TYPE(IMPORTRANGE(""https://docs.google.com/spreadsheets/d/1qFNrgBSxxEQBx4sdMB8uzwFvvIRsUBuGfUwyQgqeRN4/edit#gid=1503868715"",""A1""))=4,false))"),FALSE) -> FALSE
